Metadata-Version: 2.1
Name: django-urbano
Version: 1.4.2
Summary: Django Urbano Integration
Home-page: https://gitlab.com/linets/ecommerce/oms/integrations/django-urbano/
Author: Linets Development Team
Author-email: dteam@linets.cl
License: MIT
Platform: UNKNOWN
Requires-Python: >=3.7
